README.md
setup.cfg
setup.py
fireclass/__init__.py
fireclass/__version__.py
fireclass/document.py
fireclass/values_conversion.py
fireclass.egg-info/PKG-INFO
fireclass.egg-info/SOURCES.txt
fireclass.egg-info/dependency_links.txt
fireclass.egg-info/requires.txt
fireclass.egg-info/top_level.txt