Metadata-Version: 2.1
Name: fireclass
Version: 1.0.4
Summary: Firestore + Dataclass: declare and interact with your Firestore models using dataclasses.
Home-page: https://github.com/nabla-c0d3/fireclass
Author: Alban Diquet
Author-email: nabla.c0d3@gmail.com
License: UNKNOWN
Project-URL: Source, https://github.com/nabla-c0d3/fireclass
Keywords: dataclasses firestore google-cloud google-cloud-platform orm
Platform: UNKNOWN
Classifier: Development Status :: 4 - Beta
Classifier: Intended Audience :: Developers
Classifier: License :: OSI Approved :: MIT License
Classifier: Programming Language :: Python :: 3.7
Requires-Python: >=3.7
